README.rst
setup.cfg
setup.py
JustReleaseNotes/__init__.py
JustReleaseNotes/command_line.py
JustReleaseNotes/factory.py
JustReleaseNotes/releaseNotes.py
JustReleaseNotes.egg-info/PKG-INFO
JustReleaseNotes.egg-info/SOURCES.txt
JustReleaseNotes.egg-info/dependency_links.txt
JustReleaseNotes.egg-info/entry_points.txt
JustReleaseNotes.egg-info/not-zip-safe
JustReleaseNotes.egg-info/requires.txt
JustReleaseNotes.egg-info/top_level.txt
JustReleaseNotes/artifacters/Artifactory.py
JustReleaseNotes/artifacters/GitHubReleases.py
JustReleaseNotes/artifacters/__init__.py
JustReleaseNotes/artifacters/factory.py
JustReleaseNotes/artifacters/versioners/__init__.py
JustReleaseNotes/artifacters/versioners/dll.py
JustReleaseNotes/artifacters/versioners/factory.py
JustReleaseNotes/artifacters/versioners/ivy.py
JustReleaseNotes/issuers/AggregateIssuer.py
JustReleaseNotes/issuers/BaseIssues.py
JustReleaseNotes/issuers/GitHubIssues.py
JustReleaseNotes/issuers/JiraIssues.py
JustReleaseNotes/issuers/__init__.py
JustReleaseNotes/issuers/factory.py
JustReleaseNotes/sourcers/GitRepo.py
JustReleaseNotes/sourcers/__init__.py
JustReleaseNotes/sourcers/factory.py
JustReleaseNotes/sourcers/gitrepo.py
JustReleaseNotes/utils/EnvReplacer.py
JustReleaseNotes/utils/__init__.py
JustReleaseNotes/writers/BaseWriter.py
JustReleaseNotes/writers/GithubMarkdownWriter.py
JustReleaseNotes/writers/HtmlWriter.py
JustReleaseNotes/writers/JsonWriter.py
JustReleaseNotes/writers/MarkdownWriter.py
JustReleaseNotes/writers/StashMarkdownWriter.py
JustReleaseNotes/writers/__init__.py
JustReleaseNotes/writers/factory.py