Metadata-Version: 1.0
Name: JustReleaseNotes
Version: 0.1.11
Summary: Release notes generator package
Home-page: https://github.com/Cimpress-MCP/JustReleaseNotes
Author: Ivan Stanishev, Rafal Nowosielski
Author-email: ivan@stanishev.info, rafal@nowosielski.link
License: Apache License 2.0
Platform: UNKNOWN
